{"CO8DGJ+QabW9hujPw8CqqA==":"home.gif","qglZwtCs14qANU6PnvqFng==":"home-1.gif","/1t0BLOM3T6+1zYhQTgqgQ==":"home-2.gif","dVyX9l4qkra0Nlpr39bPPw==":"page1.gif","tSDRwMJkV8lMN5k3kCCVWw==":"page1..gif","HJBX7GzR/+bg0T+KVIIERw==":"page1-1.gif","jkkk2lUraZdfaw1cnXe24w==":"page1.rev1.gif","bYmfZj8da4xdw7HU6AGtwA==":"page1.2019-04-11%2019-31.gif","7z26Wye9vF/+cWA/GPINXw==":"page1rev2.gif","XuTSRsMUdg3fKmHhSGQVUQ==":"page1rev3.gif","QiS5Og/bp5RpQ+WgfUZwvg==":"page1rev3-1.gif","J2ET0s4OUiJI3IAPMyXi4A==":"page1rev3-2.gif","bjVSzAo3dwHq5ZeUlEAIrQ==":"page1rev3-3.gif","F3E/GeGxXBZ80omiMurDIQ==":"page1rev5.gif","Nc8uUWWxqh8SUHb7B1np5w==":"page1rev4.gif","3RAQN9YHGM0jnEeZd8gozw==":"page1rev7.gif","yw3dKP+NTkrXx0MsUgNe9Q==":"page1rev8.gif","1owqXAp2SEvh1d0GfS6XbA==":"page1rev9.gif","fLwiVinAaZpGU+aw1hS9Og==":"page1rev10.gif","RgWedVvLIv1WkQk5n63qog==":"page1rev11.gif","Sfo73ml0VGp4URz3eKXRag==":"page2.gif","PsTV89QQoOzLbqv5uJyf4g==":"page2-1.gif","54gsZehECidZh8Axs/JzLA==":"page2-2.gif","1eQqHIxUPJVUn5jl6jZp7Q==":"page2rev1.gif","GDSDe9VFItaWETF6VO71Ww==":"page2rev1-1.gif","IU3rAN221z7YQEW6i0rlwQ==":"page2rev2.gif","WB8NLZh5Xh03vJha4TVPxg==":"createdfor%20logo.001-192x108.png","GbtmQcq+RgyZXmgiLYCwjg==":"createdfor%20logo.001-192x108.png","fgG9u8nJhO42fNcnPHrM4g==":"createdfor%20logo.001-562x316.png","0Iu4xTje2cQ77NoSbuAtZg==":"createdfor%20logo.001-530x298.png","v6JeXUjW7Z5zJfLKN6Nsew==":"createdfor%20logo.001-530x298.png","wFU407KEDX+JbXuXZ4XNoA==":"createdfor%20logo.001-562x316.png","KbH3SxyS1xiGDLqnhYfcAA==":"createdfor%20logo.001-192x108.png","CgrvLd9KcabR3/ozmePPTw==":"profiel%20fns%20bw1-534x534.jpg","vd7AhAvmm/o1NEenYu23sw==":"profile%20bw%20circle%20png.001-192x108.png","zoafUMnB2NwifgpfHh88kw==":"profile%20fns%20bw%20circle%20transparent%20.001-342x342.png","kNV1ZX06Equ4CYziXukChw==":"profile%20fns%20bw%20circle%20transparent%20.001-342x342.png"}